dj_libcloud-0.2.0.dist-info/DESCRIPTION.rst
dj_libcloud-0.2.0.dist-info/METADATA
dj_libcloud-0.2.0.dist-info/metadata.json
dj_libcloud-0.2.0.dist-info/RECORD
dj_libcloud-0.2.0.dist-info/top_level.txt
dj_libcloud-0.2.0.dist-info/WHEEL
djlibcloud/__init__.py
djlibcloud/storage.py
