Metadata-Version: 2.0
Name: dj-libcloud
Version: 0.2.0
Summary: Adds easy python 3 and 2.7 support to Django for management of static assets.
Home-page: https://github.com/pydanny/dj-libcloud
Author: Daniel Greenfeld
Author-email: pydanny@gmail.com
License: BSD
Keywords: dj-libcloud
Platform: UNKNOWN
Classifier: Development Status :: 3 - Alpha
Classifier: Framework :: Django
Classifier: Intended Audience :: Developers
Classifier: License :: OSI Approved :: BSD License
Classifier: Natural Language :: English
Classifier: Programming Language :: Python :: 2
Classifier: Programming Language :: Python :: 2.7
Classifier: Programming Language :: Python :: 3
Classifier: Programming Language :: Python :: 3.3
Requires-Dist: apache-libcloud (>=0.14.1)
Requires-Dist: django (>=1.6.0)
